simp_sql/__init__.py
simp_sql/db_connection.py
simp_sql/query_generator.py
timp_sql/__init__.py
timp_sql/db_connection.py
timp_sql/query_generator.py
timp_sql-0.1.1.dist-info/LICENSE
timp_sql-0.1.1.dist-info/METADATA
timp_sql-0.1.1.dist-info/WHEEL
timp_sql-0.1.1.dist-info/top_level.txt
timp_sql-0.1.1.dist-info/RECORD
